aiosonic/__init__.py
aiosonic/base_client.py
aiosonic/client.py
aiosonic/connection.py
aiosonic/connectors.py
aiosonic/exceptions.py
aiosonic/http2.py
aiosonic/http_parser.py
aiosonic/multipart.py
aiosonic/pools.py
aiosonic/proxy.py
aiosonic/resolver.py
aiosonic/sse_client.py
aiosonic/sse_config.py
aiosonic/tcp_helpers.py
aiosonic/timeout.py
aiosonic/types.py
aiosonic/utils.py
aiosonic/version.py
aiosonic/web_socket_client.py
aiosonic_utils/__init__.py
aiosonic_utils/structures.py
aiosonic-0.29.0.dist-info/LICENSE
aiosonic-0.29.0.dist-info/METADATA
aiosonic-0.29.0.dist-info/WHEEL
aiosonic-0.29.0.dist-info/RECORD
