Metadata-Version: 2.1
Name: aiosonic
Version: 0.29.0
Summary: Async HTTP/WebSocket client
Home-page: https://aiosonic.readthedocs.io/en/latest/
License: MIT
Author: Johanderson Mogollon
Author-email: johander1822@gmail.com
Requires-Python: >=3.8.0,<3.14
Classifier: Development Status :: 5 - Production/Stable
Classifier: Intended Audience :: Developers
Classifier: License :: OSI Approved :: MIT License
Classifier: Operating System :: OS Independent
Classifier: Programming Language :: Python :: 3
Classifier: Programming Language :: Python :: 3.8
Classifier: Programming Language :: Python :: 3.9
Classifier: Programming Language :: Python :: 3.10
Classifier: Programming Language :: Python :: 3.11
Classifier: Programming Language :: Python :: 3.12
Classifier: Programming Language :: Python :: 3 :: Only
Classifier: Programming Language :: Python :: Implementation :: CPython
Classifier: Programming Language :: Python :: Implementation :: PyPy
Classifier: Topic :: Internet :: WWW/HTTP
Requires-Dist: charset-normalizer (>=2.0.0,<4.0.0)
Requires-Dist: h2 (>=4.1.0,<5.0.0)
Requires-Dist: onecache (>=0.7.0,<0.8.0)
Project-URL: Repository, https://github.com/sonic182/aiosonic
